python_input/__init__.py
python_input/_input.py
python_input-0.1.5.dist-info/METADATA
python_input-0.1.5.dist-info/WHEEL
python_input-0.1.5.dist-info/RECORD
