Metadata-Version: 2.1
Name: python-input
Version: 0.1.5
Summary: 
Home-page: https://github.com/Will-J-Gale/python-input
Author: Will Gale
Author-email: willjgale@outlook.com
Requires-Python: >=3.8,<4.0
Classifier: Programming Language :: Python :: 3
Classifier: Programming Language :: Python :: 3.8
Classifier: Programming Language :: Python :: 3.9
Classifier: Programming Language :: Python :: 3.10
Classifier: Programming Language :: Python :: 3.11
Requires-Dist: pynput (>=1.7.6,<2.0.0)
